my_package_himanshi/__init__.py
my_package_himanshi/setup.py
my_package_himanshi/zunno.py
my_package_himanshi-0.3.dist-info/METADATA
my_package_himanshi-0.3.dist-info/WHEEL
my_package_himanshi-0.3.dist-info/top_level.txt
my_package_himanshi-0.3.dist-info/RECORD
