Metadata-Version: 2.4
Name: my-package-himanshi
Version: 0.3
Summary: Python wrapper to interact with Ollama-served Gemma LLM
Home-page: https://github.com/yourusername/my-package-himanshi
Author: Himanshi
Author-email: Himanshi <your-email@example.com>
Requires-Python: >=3.7
Requires-Dist: requests
Dynamic: author
Dynamic: home-page
Dynamic: requires-python
